README.txt
setup.py
src/erp5/__init__.py
src/erp5.extension.sectionextender.egg-info/PKG-INFO
src/erp5.extension.sectionextender.egg-info/SOURCES.txt
src/erp5.extension.sectionextender.egg-info/dependency_links.txt
src/erp5.extension.sectionextender.egg-info/entry_points.txt
src/erp5.extension.sectionextender.egg-info/namespace_packages.txt
src/erp5.extension.sectionextender.egg-info/requires.txt
src/erp5.extension.sectionextender.egg-info/top_level.txt
src/erp5/extension/__init__.py
src/erp5/extension/sectionextender/__init__.py