Metadata-Version: 1.0
Name: erp5.extension.sectionextender
Version: 0.3.1
Summary: Buildout extension to extend only sections in parts
Home-page: https://github.com/Apkawa/erp5.extension.sectionextender
Author: Arnaud Fontaine
Author-email: arnaud.fontaine@nexedi.com
License: ZPL 2.1
Keywords: buildout extension sections
Platform: UNKNOWN
Classifier: License :: OSI Approved :: Zope Public License
Classifier: Framework :: Buildout
